{
    "name": "Б.ЭК 2007",
    "subjects": {
        "Вторник": [
            {
                "is_even": false,
                "name": "Иностранный  язык (пр) Уч-422,  524",
                "start_time": 8.3
            },
            {
                "is_even": false,
                "name": "Основы  экономики  организации  (лек)  Уч-509",
                "start_time": 10.15
            },
            {
                "is_even": true,
                "name": "Основы  экономики  организации  (лек)  Уч-509",
                "start_time": 10.15
            },
            {
                "is_even": false,
                "name": "Основы  экономики  организации  (пр)  Уч-509",
                "start_time": 12.15
            },
            {
                "is_even": false,
                "name": "Библиотека  20.10, 27.10 Хт-101",
                "start_time": 14.0
            },
            {
                "is_even": true,
                "name": "Библиотека  20.10, 27.10 Хт-101",
                "start_time": 14.0
            }
        ],
        "Понедельник": [
            {
                "is_even": false,
                "name": "Элетив.  дисц.. по физич.  кул-ре и спорту",
                "start_time": 8.3
            },
            {
                "is_even": true,
                "name": "Элетив.  дисц.. по физич.  кул-ре и спорту",
                "start_time": 8.3
            },
            {
                "is_even": false,
                "name": "Речевая  и делов. коммуникация  (лек) Хт-112",
                "start_time": 10.15
            },
            {
                "is_even": true,
                "name": "История  экономики  (лек) Уч-204",
                "start_time": 10.15
            },
            {
                "is_even": false,
                "name": "Речевая  и делов. коммуникация  (пр) Уч-520",
                "start_time": 12.15
            },
            {
                "is_even": true,
                "name": "История  экономики  (пр) Уч-204",
                "start_time": 12.15
            }
        ],
        "Пятница": [
            {
                "is_even": false,
                "name": "Математика  (лек) Уч-403",
                "start_time": 8.3
            },
            {
                "is_even": false,
                "name": "Миров.  инфор. ресурсы  (лаб) Уч-302",
                "start_time": 10.15
            },
            {
                "is_even": true,
                "name": "Миров.  инфор. ресурсы  (лаб) Уч-302",
                "start_time": 10.15
            },
            {
                "is_even": false,
                "name": "Математика  (пр) Уч-403",
                "start_time": 12.15
            },
            {
                "is_even": true,
                "name": "Математика  (пр) Уч-403",
                "start_time": 12.15
            }
        ],
        "Среда": [
            {
                "is_even": false,
                "name": "Микроэкономика  (пр) Уч-221",
                "start_time": 8.3
            },
            {
                "is_even": false,
                "name": "Миров.  инфор. ресурсы  (лек) Уч-509",
                "start_time": 10.15
            },
            {
                "is_even": true,
                "name": "Культурология  (пр) Хт-128",
                "start_time": 10.15
            },
            {
                "is_even": false,
                "name": "Культурология  (лек) Хт-112",
                "start_time": 12.15
            },
            {
                "is_even": true,
                "name": "Микроэкономика  (пр) Уч-516",
                "start_time": 12.15
            }
        ],
        "Четверг": [
            {
                "is_even": true,
                "name": "Информатика  (лек) Уч-403",
                "start_time": 8.3
            },
            {
                "is_even": false,
                "name": "Микроэкономика  (лек) Уч-221",
                "start_time": 10.15
            },
            {
                "is_even": false,
                "name": "Информатика  (лаб) Уч-408",
                "start_time": 12.15
            },
            {
                "is_even": true,
                "name": "Информатика  (лаб) Уч-408",
                "start_time": 12.15
            }
        ]
    }
}